jupyterlab_apod/__init__.py
jupyterlab_apod/_version.py
jupyterlab_apod-3.5.0.data/data/share/jupyter/labextensions/jupyterlab_apod/package.json
jupyterlab_apod-3.5.0.data/data/share/jupyter/labextensions/jupyterlab_apod/static/568.1665146b74c5ac9c2244.js
jupyterlab_apod-3.5.0.data/data/share/jupyter/labextensions/jupyterlab_apod/static/747.06231139f0e4d0bae2db.js
jupyterlab_apod-3.5.0.data/data/share/jupyter/labextensions/jupyterlab_apod/static/remoteEntry.778df5077d15eaf5d9bd.js
jupyterlab_apod-3.5.0.data/data/share/jupyter/labextensions/jupyterlab_apod/static/style.js
jupyterlab_apod-3.5.0.data/data/share/jupyter/labextensions/jupyterlab_apod/static/third-party-licenses.json
jupyterlab_apod-3.5.0.data/data/share/jupyter/labextensions/jupyterlab_apod/install.json
jupyterlab_apod-3.5.0.dist-info/METADATA
jupyterlab_apod-3.5.0.dist-info/WHEEL
jupyterlab_apod-3.5.0.dist-info/licenses/LICENSE
jupyterlab_apod-3.5.0.dist-info/RECORD
