Metadata-Version: 2.1
Name: jupyterlab_apod
Version: 3.5.0
Summary: Show a random NASA Astronomy Picture of the Day in a JupyterLab panel
Project-URL: Homepage, https://github.com/jupyterlab/jupyterlab_apod
Project-URL: Bug Tracker, https://github.com/jupyterlab/jupyterlab_apod/issues
Project-URL: Repository, https://github.com/jupyterlab/jupyterlab_apod.git
Author-email: Your Name <your@name.org>
License: BSD 3-Clause License
License-File: LICENSE
Classifier: Framework :: Jupyter
Classifier: Framework :: Jupyter :: JupyterLab
Classifier: Framework :: Jupyter :: JupyterLab :: 3
Classifier: Framework :: Jupyter :: JupyterLab :: Extensions
Classifier: Framework :: Jupyter :: JupyterLab :: Extensions :: Prebuilt
Classifier: License :: OSI Approved :: BSD License
Classifier: Programming Language :: Python
Classifier: Programming Language :: Python :: 3
Classifier: Programming Language :: Python :: 3.7
Classifier: Programming Language :: Python :: 3.8
Classifier: Programming Language :: Python :: 3.9
Classifier: Programming Language :: Python :: 3.10
Classifier: Programming Language :: Python :: 3.11
Requires-Python: >=3.7
